BHlib.py
BHlib-0.0.1.dist-info/LICENSE
BHlib-0.0.1.dist-info/METADATA
BHlib-0.0.1.dist-info/WHEEL
BHlib-0.0.1.dist-info/top_level.txt
BHlib-0.0.1.dist-info/RECORD
